{
  "enabled": true,
  "version": "2.0.0",
  "ultima_actualizacion": "2025-10-27T19:50:00Z",
  "moneda": "ARS",
  "notas": "Sistema de precios normales con overrides de promoción configurable. Los overrides solo se aplican si promo_config.activa es true.",
  "hero": {
    "titulo": "Conecta sin Límites",
    "descripcion": "Planes flexibles y velocidad premium para tu estilo de vida digital",
    "promocion": {
      "habilitada": false,
      "texto": "⚡ PROMOCIÓN ESPECIAL - 30% OFF EN TODOS LOS PLANES",
      "borderColor": "border-rose-500/40",
      "bgColor": "bg-slate-900/60",
      "textColor": "text-rose-300",
      "iconColor": "text-rose-400",
      "shadowColor": "shadow-rose-500/30",
      "comentario": "Estilo minimalista glassmorphism que combina con el timer"
    }
  },
  "planes_disponibles": {
    "21": "Plan Básico 7D (1 dispositivo - 7 días)",
    "22": "Plan Doble 7D (2 dispositivos - 7 días)",
    "23": "Plan Triple 7D (3 dispositivos - 7 días)",
    "24": "Plan Familiar 7D (4 dispositivos - 7 días)",
    "25": "Plan Básico 15D (1 dispositivo - 15 días)",
    "26": "Plan Doble 15D (2 dispositivos - 15 días)",
    "27": "Plan Triple 15D (3 dispositivos - 15 días)",
    "28": "Plan Familiar 15D (4 dispositivos - 15 días)",
    "29": "Plan Básico 30D (1 dispositivo - 30 días)",
    "30": "Plan Doble 30D (2 dispositivos - 30 días)",
    "31": "Plan Triple 30D (3 dispositivos - 30 días)",
    "32": "Plan Familiar 30D (4 dispositivos - 30 días)",
    "33": "Plan Básico 3D (1 dispositivo - 3 días)",
    "34": "Plan Doble 3D (2 dispositivos - 3 días)",
    "35": "Plan Triple 3D (3 dispositivos - 3 días)",
    "36": "Plan Familiar 3D (4 dispositivos - 3 días)",
    "37": "Plan Básico 20D (1 dispositivo - 20 días)",
    "38": "Plan Doble 20D (2 dispositivos - 20 días)",
    "39": "Plan Triple 20D (3 dispositivos - 20 días)",
    "40": "Plan Familiar 20D (4 dispositivos - 20 días)",
    "41": "Plan Básico 25D (1 dispositivo - 25 días)",
    "42": "Plan Doble 25D (2 dispositivos - 25 días)",
    "43": "Plan Triple 25D (3 dispositivos - 25 días)",
    "44": "Plan Familiar 25D (4 dispositivos - 25 días)"
  },
  "precios_normales": {
    "21": 4000,
    "22": 6000,
    "23": 9000,
    "24": 11000,
    "25": 6000,
    "26": 9000,
    "27": 12000,
    "28": 15000,
    "29": 8000,
    "30": 12000,
    "31": 15000,
    "32": 18000,
    "33": 2000,
    "34": 3000,
    "35": 4500,
    "36": 5500,
    "37": 6500,
    "38": 9500,
    "39": 12500,
    "40": 15500,
    "41": 7000,
    "42": 10000,
    "43": 13000,
    "44": 16000
  },
  "overrides": {
    "_comentario": "Precios con 30% descuento para promoción - IDs corregidos para coincidir con planes",
    "21": { "precio": 2800 },
    "22": { "precio": 4200 },
    "23": { "precio": 6300 },
    "24": { "precio": 7700 },
    "25": { "precio": 4200 },
    "26": { "precio": 6300 },
    "27": { "precio": 8400 },
    "28": { "precio": 10500 },
    "29": { "precio": 5600 },
    "30": { "precio": 8400 },
    "31": { "precio": 10500 },
    "32": { "precio": 12600 },
    "33": { "precio": 3 },
    "34": { "precio": 2100 },
    "35": { "precio": 3150 },
    "36": { "precio": 3850 },
    "37": { "precio": 4550 },
    "38": { "precio": 6650 },
    "39": { "precio": 8750 },
    "40": { "precio": 10850 },
    "41": { "precio": 4900 },
    "42": { "precio": 7000 },
    "43": { "precio": 9100 },
    "44": { "precio": 11200 }
  },
  "promo_config": {
    "activa": false,
    "activada_en": "2025-10-31T20:18:00Z",
    "duracion_horas": 12,
    "auto_desactivar": true,
    "_instrucciones": "POST /api/config/activar-promo { duracion_horas: number }"
  }
}
